visitor/__init__.py
visitor/__main__.py
visitor/host.json
visitor/index.py
digolds_cn-1.0.0.dist-info/LICENSE
digolds_cn-1.0.0.dist-info/METADATA
digolds_cn-1.0.0.dist-info/WHEEL
digolds_cn-1.0.0.dist-info/entry_points.txt
digolds_cn-1.0.0.dist-info/top_level.txt
digolds_cn-1.0.0.dist-info/RECORD
