Metadata-Version: 2.1
Name: digolds-cn
Version: 1.0.0
Summary: Visit digolds's home page
Author-email: "digolds.cn" <founders@digolds.cn>
License: MIT License        
Project-URL: repository, https://github.com/digolds/visitor
Project-URL: documentation, https://www.digolds.cn/article/001657582121249b1a45f4cf3b7468483136c61ac159786000
Keywords: digolds,digolds.cn
Classifier: License :: OSI Approved :: MIT License
Classifier: Programming Language :: Python :: 3
Requires-Python: >=3.7
License-File: LICENSE
Requires-Dist: requests (>=2.24.0)
Provides-Extra: build
Requires-Dist: build ; extra == 'build'
Requires-Dist: twine ; extra == 'build'
Provides-Extra: dev
Requires-Dist: pytest ; extra == 'dev'
